hqxpack/SparkApi.py
hqxpack/__init__.py
hqxpack/agent.py
hqxpack/audio.py
hqxpack/cloud.py
hqxpack/coze.py
hqxpack/cozePro.py
hqxpack/cozefile.py
hqxpack/deepseek.py
hqxpack/getip.py
hqxpack/kimi.py
hqxpack/kimiv2.py
hqxpack/mail.py
hqxpack/suno.py
hqxpack/ttp.py
hqxpack-2025.7.1.dist-info/licenses/LICENSE
hqxpack-2025.7.1.dist-info/METADATA
hqxpack-2025.7.1.dist-info/WHEEL
hqxpack-2025.7.1.dist-info/top_level.txt
hqxpack-2025.7.1.dist-info/RECORD
